fds/__init__.py
fds/sdk/__init__.py
fds/sdk/InvestmentResearch/__init__.py
fds/sdk/InvestmentResearch/api_client.py
fds/sdk/InvestmentResearch/configuration.py
fds/sdk/InvestmentResearch/exceptions.py
fds/sdk/InvestmentResearch/model_utils.py
fds/sdk/InvestmentResearch/rest.py
fds/sdk/InvestmentResearch/api/__init__.py
fds/sdk/InvestmentResearch/api/meta_api.py
fds/sdk/InvestmentResearch/api/research_api.py
fds/sdk/InvestmentResearch/apis/__init__.py
fds/sdk/InvestmentResearch/model/__init__.py
fds/sdk/InvestmentResearch/model/analyst_id.py
fds/sdk/InvestmentResearch/model/asset_classes.py
fds/sdk/InvestmentResearch/model/asset_response.py
fds/sdk/InvestmentResearch/model/asset_types.py
fds/sdk/InvestmentResearch/model/asset_types_response.py
fds/sdk/InvestmentResearch/model/categories.py
fds/sdk/InvestmentResearch/model/categories_response.py
fds/sdk/InvestmentResearch/model/categories_response_object.py
fds/sdk/InvestmentResearch/model/contributor_id.py
fds/sdk/InvestmentResearch/model/count_request.py
fds/sdk/InvestmentResearch/model/count_request_body.py
fds/sdk/InvestmentResearch/model/count_response.py
fds/sdk/InvestmentResearch/model/count_response_object.py
fds/sdk/InvestmentResearch/model/coverage_actions.py
fds/sdk/InvestmentResearch/model/disciplines.py
fds/sdk/InvestmentResearch/model/document.py
fds/sdk/InvestmentResearch/model/error_example.py
fds/sdk/InvestmentResearch/model/error_response.py
fds/sdk/InvestmentResearch/model/ids.py
fds/sdk/InvestmentResearch/model/invalid_id_error_object.py
fds/sdk/InvestmentResearch/model/investment_research_response.py
fds/sdk/InvestmentResearch/model/investment_research_response_items.py
fds/sdk/InvestmentResearch/model/investment_research_response_meta.py
fds/sdk/InvestmentResearch/model/investment_research_response_meta_pagination.py
fds/sdk/InvestmentResearch/model/issuer_types.py
fds/sdk/InvestmentResearch/model/periodicities.py
fds/sdk/InvestmentResearch/model/purposes.py
fds_sdk_investmentresearch-0.1.1.dist-info/licenses/LICENSE
fds_sdk_investmentresearch-0.1.1.dist-info/METADATA
fds_sdk_investmentresearch-0.1.1.dist-info/WHEEL
fds_sdk_investmentresearch-0.1.1.dist-info/top_level.txt
fds_sdk_investmentresearch-0.1.1.dist-info/RECORD
